Metadata-Version: 2.1
Name: apples
Version: 2.0.10
Summary: APPLES: a distance-based phylogenetic placement tool
Home-page: https://github.com/balabanmetin/apples
Author: Metin Balaban
Author-email: balaban@ucsd.edu
License: UNKNOWN
Platform: UNKNOWN
